solubilityccs/__init__.py
solubilityccs/_version.py
solubilityccs/fluid.py
solubilityccs/neqsim_functions.py
solubilityccs/path_utils.py
solubilityccs/sulfuric_acid_activity.py
solubilityccs/Database/COMP.csv
solubilityccs/Database/Properties.csv
solubilityccs/Database/WaterActivityH2SO4.csv
solubilityccs-0.8.7.dist-info/licenses/LICENSE
solubilityccs-0.8.7.dist-info/METADATA
solubilityccs-0.8.7.dist-info/WHEEL
solubilityccs-0.8.7.dist-info/top_level.txt
solubilityccs-0.8.7.dist-info/RECORD
