Metadata-Version: 2.4
Name: solubilityCCS
Version: 0.8.7
Summary: A Python package for analyzing solubility and acid formation behavior in Carbon Capture and Storage (CCS) systems
Author: SolubilityCCS Contributors
Maintainer: SolubilityCCS Contributors
License-Expression: Apache-2.0
Project-URL: Homepage, https://github.com/your-username/SolubilityCCS
Project-URL: Documentation, https://github.com/your-username/SolubilityCCS#readme
Project-URL: Repository, https://github.com/your-username/SolubilityCCS
Project-URL: Bug Tracker, https://github.com/your-username/SolubilityCCS/issues
Keywords: carbon-capture,ccs,solubility,acid-formation,phase-behavior,thermodynamics
Classifier: Development Status :: 4 - Beta
Classifier: Intended Audience :: Science/Research
Classifier: Operating System :: OS Independent
Classifier: Programming Language :: Python :: 3
Classifier: Programming Language :: Python :: 3.9
Classifier: Programming Language :: Python :: 3.10
Classifier: Programming Language :: Python :: 3.11
Classifier: Programming Language :: Python :: 3.12
Classifier: Topic :: Scientific/Engineering :: Chemistry
Classifier: Topic :: Scientific/Engineering :: Physics
Requires-Python: >=3.9
License-File: LICENSE
Requires-Dist: neqsim
Requires-Dist: scipy
Requires-Dist: matplotlib
Requires-Dist: pandas
Requires-Dist: numpy
Provides-Extra: dev
Requires-Dist: pytest; extra == "dev"
Requires-Dist: pytest-cov; extra == "dev"
Requires-Dist: pytest-mock; extra == "dev"
Requires-Dist: black; extra == "dev"
Requires-Dist: isort; extra == "dev"
Requires-Dist: mypy; extra == "dev"
Requires-Dist: pre-commit; extra == "dev"
Provides-Extra: notebook
Requires-Dist: ipykernel; extra == "notebook"
Requires-Dist: jupyter; extra == "notebook"
Requires-Dist: notebook; extra == "notebook"
Dynamic: license-file
